MANIFEST.in
README.md
pyproject.toml
setup.py
amuse_evtwin.egg-info/PKG-INFO
amuse_evtwin.egg-info/SOURCES.txt
amuse_evtwin.egg-info/dependency_links.txt
amuse_evtwin.egg-info/requires.txt
amuse_evtwin.egg-info/top_level.txt
src/amuse/community/evtwin/Makefile
src/amuse/community/evtwin/__init__.py
src/amuse/community/evtwin/_version.py
src/amuse/community/evtwin/interface.py
src/amuse/community/evtwin/data/README.txt
src/amuse/community/evtwin/data/input/input/lt2ubv.dat
src/amuse/community/evtwin/data/input/input/mutate.dat
src/amuse/community/evtwin/data/input/input/nrates.dat
src/amuse/community/evtwin/data/input/input/nucdata.dat
src/amuse/community/evtwin/data/input/input/physinfo.dat
src/amuse/community/evtwin/data/input/input/poly32.dat
src/amuse/community/evtwin/data/input/input/rates.dat
src/amuse/community/evtwin/data/input/input/zahb.dat
src/amuse/community/evtwin/data/input/input/zahb02.mod
src/amuse/community/evtwin/data/input/input/zams_start.mas
src/amuse/community/evtwin/data/input/input/zams_start.out
src/amuse/community/evtwin/data/input/input/COtables/COtables_z00001
src/amuse/community/evtwin/data/input/input/COtables/COtables_z00003
src/amuse/community/evtwin/data/input/input/COtables/COtables_z0001
src/amuse/community/evtwin/data/input/input/COtables/COtables_z0003
src/amuse/community/evtwin/data/input/input/COtables/COtables_z001
src/amuse/community/evtwin/data/input/input/COtables/COtables_z002
src/amuse/community/evtwin/data/input/input/COtables/COtables_z003
src/amuse/community/evtwin/data/input/input/COtables/COtables_z004
src/amuse/community/evtwin/data/input/input/COtables/COtables_z006
src/amuse/community/evtwin/data/input/input/COtables/COtables_z008
src/amuse/community/evtwin/data/input/input/COtables/COtables_z01
src/amuse/community/evtwin/data/input/input/COtables/COtables_z02
src/amuse/community/evtwin/data/input/input/COtables/COtables_z03
src/amuse/community/evtwin/data/input/input/COtables/COtables_z04
src/amuse/community/evtwin/data/input/input/COtables/COtables_z05
src/amuse/community/evtwin/data/input/input/amuse/README
src/amuse/community/evtwin/data/input/input/amuse/init.dat
